termcc/__init__.py
termcc/cc.py
termcc/core.py
termcc/query.py
termcc/run.py
termcc/unicodes_codec.py
termcc/helper/__init__.py
termcc/helper/logger.py
termcc/helper/time.py
termcc/helper/trace.py
termcc-2019.8.1.dist-info/METADATA
termcc-2019.8.1.dist-info/WHEEL
termcc-2019.8.1.dist-info/entry_points.txt
termcc-2019.8.1.dist-info/top_level.txt
termcc-2019.8.1.dist-info/RECORD
