Metadata-Version: 2.1
Name: termcc
Version: 2019.8.1
Summary: give you some color to see see(chinese idiom) in terminal
Home-page: https://github.com/pingf/termcc.git
Author: dameng
Author-email: pingf0@gmail.com
License: MIT
Platform: any
Classifier: Intended Audience :: Developers
Classifier: License :: OSI Approved :: MIT License
Classifier: Operating System :: OS Independent
Classifier: Programming Language :: Python
Classifier: Topic :: Software Development :: Libraries :: Python Modules
Requires-Dist: logbook
Requires-Dist: pendulum
Requires-Dist: terminaltables
